napalm_logs/__init__.py
napalm_logs/auth.py
napalm_logs/base.py
napalm_logs/device.py
napalm_logs/exceptions.py
napalm_logs/listener_proc.py
napalm_logs/proc.py
napalm_logs/pub_proxy.py
napalm_logs/publisher.py
napalm_logs/server.py
napalm_logs/buffer/__init__.py
napalm_logs/buffer/memory.py
napalm_logs/buffer/redisbuf.py
napalm_logs/config/__init__.py
napalm_logs/config/eos/AGENT_INITIALIZED.yml
napalm_logs/config/eos/BFD_STATE_CHANGE.yml
napalm_logs/config/eos/BGP_NEIGHBOR_STATE_CHANGED.yml
napalm_logs/config/eos/BGP_PREFIX_LIMIT_EXCEEDED.yml
napalm_logs/config/eos/INTERFACE_DOWN.yml
napalm_logs/config/eos/INTERFACE_UP.yml
napalm_logs/config/eos/ISIS_NEIGHBOR_DOWN.yml
napalm_logs/config/eos/ISIS_NEIGHBOR_UP.yml
napalm_logs/config/eos/MAINTENANCE_MODE.yml
napalm_logs/config/eos/PROCESS_RESTART.yml
napalm_logs/config/eos/PROCESS_STARTED.yml
napalm_logs/config/eos/PROCESS_TERMINATED.yml
napalm_logs/config/eos/USER_ENTER_CONFIG_MODE.yml
napalm_logs/config/eos/USER_EXITED_CONFIG_MODE.yml
napalm_logs/config/eos/USER_WRITE_CONFIG.yml
napalm_logs/config/eos/init.yml
napalm_logs/config/fortinet/FORWARD_TRAFFIC.yml
napalm_logs/config/fortinet/LOCAL_TRAFFIC.yml
napalm_logs/config/fortinet/init.yml
napalm_logs/config/huawei/INTERFACE_DOWN.yml
napalm_logs/config/huawei/INTERFACE_UP.yml
napalm_logs/config/huawei/init.yml
napalm_logs/config/ios/INTERFACE_DOWN.yml
napalm_logs/config/ios/INTERFACE_UP.yml
napalm_logs/config/ios/OSPF_NEIGHBOR_DOWN.yml
napalm_logs/config/ios/OSPF_NEIGHBOR_UP.yml
napalm_logs/config/ios/USER_EXIT_CONFIG_MODE.yml
napalm_logs/config/ios/init.yml
napalm_logs/config/iosxr/BGP_PREFIX_THRESH_EXCEEDED.yml
napalm_logs/config/iosxr/CONFIGURATION_COMMIT_COMPLETED.yml
napalm_logs/config/iosxr/INTERFACE_DOWN.yml
napalm_logs/config/iosxr/INTERFACE_UP.yml
napalm_logs/config/iosxr/ISIS_NEIGHBOR_DOWN.yml
napalm_logs/config/iosxr/ISIS_NEIGHBOR_UP.yml
napalm_logs/config/iosxr/NTP_SERVER_UNREACHABLE.yml
napalm_logs/config/iosxr/init.yml
napalm_logs-0.11.0.dist-info/LICENSE
napalm_logs-0.11.0.dist-info/METADATA
napalm_logs-0.11.0.dist-info/WHEEL
napalm_logs-0.11.0.dist-info/entry_points.txt
napalm_logs-0.11.0.dist-info/top_level.txt
napalm_logs-0.11.0.dist-info/RECORD
