Metadata-Version: 2.1
Name: napalm-logs
Version: 0.11.0
Summary: Network Automation and Programmability Abstraction Layer with Multivendor support: syslog parser
Home-page: https://github.com/napalm-automation/napalm-logs
Author: Mircea Ulinic
Author-email: ping@mirceaulinic.net
License: Apache License 2.0
Keywords: napalm,syslog,zeromq,engine
Platform: UNKNOWN
Classifier: Development Status :: 5 - Production/Stable
Classifier: Topic :: Utilities
Classifier: Topic :: System :: Networking
Classifier: Programming Language :: Python
Classifier: Programming Language :: Python :: 2
Classifier: Programming Language :: Python :: 2.7
Classifier: Programming Language :: Python :: 3
Classifier: Programming Language :: Python :: 3.5
Classifier: Programming Language :: Python :: 3.6
Classifier: Programming Language :: Python :: 3.7
Classifier: Operating System :: POSIX :: Linux
Classifier: Operating System :: MacOS
Classifier: Intended Audience :: Developers
License-File: LICENSE
Requires-Dist: pyzmq
Requires-Dist: pyyaml
Requires-Dist: pynacl
Requires-Dist: dateparser
Requires-Dist: sentry-sdk
Requires-Dist: u-msgpack-python
Requires-Dist: prometheus-client
